LICENSE
README.md
pyproject.toml
setup.py
cpg_utils/__init__.py
cpg_utils/auth.py
cpg_utils/cloud.py
cpg_utils/cloudpath_hail_az.py
cpg_utils/config.py
cpg_utils/creds.py
cpg_utils/deploy_config.py
cpg_utils/git.py
cpg_utils/hail_batch.py
cpg_utils/secrets.py
cpg_utils/slack.py
cpg_utils/storage.py
cpg_utils_ms.egg-info/PKG-INFO
cpg_utils_ms.egg-info/SOURCES.txt
cpg_utils_ms.egg-info/dependency_links.txt
cpg_utils_ms.egg-info/requires.txt
cpg_utils_ms.egg-info/top_level.txt
test/__init__.py
test/conftest.py
test/test_auth.py
test/test_cloudpath_hail_az.py
test/test_config.py
test/test_secrets.py
test/test_storage.py