Metadata-Version: 2.1
Name: cpg-utils-ms
Version: 1.3.6
Summary: Library of convenience functions specific to the CPG (MS version)
Home-page: https://github.com/gregsmi/cpg-utils
License: MIT
Keywords: bioinformatics
Classifier: Environment :: Console
Classifier: Intended Audience :: Science/Research
Classifier: License :: OSI Approved :: MIT License
Classifier: Natural Language :: English
Classifier: Operating System :: MacOS :: MacOS X
Classifier: Operating System :: POSIX
Classifier: Operating System :: Unix
Classifier: Programming Language :: Python
Classifier: Topic :: Scientific/Engineering
Classifier: Topic :: Scientific/Engineering :: Bio-Informatics
Provides-Extra: test
License-File: LICENSE
